trashpandas/__init__.py
trashpandas/conversion.py
trashpandas/csv.py
trashpandas/hdf5.py
trashpandas/interfaces.py
trashpandas/pickle.py
trashpandas/py.typed
trashpandas/sql.py
trashpandas/utils.py
trashpandas-0.0.10.dist-info/LICENSE
trashpandas-0.0.10.dist-info/METADATA
trashpandas-0.0.10.dist-info/WHEEL
trashpandas-0.0.10.dist-info/top_level.txt
trashpandas-0.0.10.dist-info/RECORD
